mini_rec_sys/__init__.py
mini_rec_sys/constants.py
mini_rec_sys/data/__init__.py
mini_rec_sys/data/datasets.py
mini_rec_sys/data/samplers.py
mini_rec_sys/data/session.py
mini_rec_sys/encoders/__init__.py
mini_rec_sys/encoders/encoders.py
mini_rec_sys/evaluators/__init__.py
mini_rec_sys/evaluators/evaluators.py
mini_rec_sys/sample_data/__init__.py
mini_rec_sys/sample_data/msmarco_reranking/.gitignore
mini_rec_sys/sample_data/msmarco_reranking/README.md
mini_rec_sys/sample_data/msmarco_reranking/__init__.py
mini_rec_sys/sample_data/msmarco_reranking/download.sh
mini_rec_sys/sample_data/msmarco_reranking/generate_data.py
mini_rec_sys/sample_data/msmarco_reranking/msmarco_sample_items.json
mini_rec_sys/sample_data/msmarco_reranking/msmarco_sample_sessions.json
mini_rec_sys/scorers/BM25Scorer.py
mini_rec_sys/scorers/BaseScorer.py
mini_rec_sys/scorers/DenseScorer.py
mini_rec_sys/scorers/__init__.py
mini_rec_sys/trainers/DPRModel.py
mini_rec_sys/trainers/__init__.py
mini_rec_sys/trainers/base_trainers.py
mini_rec_sys/utils.py
mini_rec_sys-0.1.4.dist-info/LICENSE
mini_rec_sys-0.1.4.dist-info/METADATA
mini_rec_sys-0.1.4.dist-info/WHEEL
mini_rec_sys-0.1.4.dist-info/RECORD
